birdnet/__init__.py
birdnet/argparse_helper.py
birdnet/backends.py
birdnet/base.py
birdnet/benchmark_script.py
birdnet/globals.py
birdnet/helper.py
birdnet/local_data.py
birdnet/logging_utils.py
birdnet/model_loader.py
birdnet/model_loader.pyi
birdnet/py.typed
birdnet/shm.py
birdnet/utils.py
birdnet/acoustic_models/__init__.py
birdnet/acoustic_models/base.py
birdnet/acoustic_models/inference/__init__.py
birdnet/acoustic_models/inference/benchmarking.py
birdnet/acoustic_models/inference/consumer.py
birdnet/acoustic_models/inference/files_analyzer.py
birdnet/acoustic_models/inference/perf_tracker.py
birdnet/acoustic_models/inference/producer.py
birdnet/acoustic_models/inference/result_base.py
birdnet/acoustic_models/inference/tensor.py
birdnet/acoustic_models/inference/worker.py
birdnet/acoustic_models/inference/encoding/__init__.py
birdnet/acoustic_models/inference/encoding/benchmarking.py
birdnet/acoustic_models/inference/encoding/result.py
birdnet/acoustic_models/inference/encoding/tensor.py
birdnet/acoustic_models/inference/encoding/worker.py
birdnet/acoustic_models/inference/prediction/__init__.py
birdnet/acoustic_models/inference/prediction/benchmarking.py
birdnet/acoustic_models/inference/prediction/result.py
birdnet/acoustic_models/inference/prediction/tensor.py
birdnet/acoustic_models/inference/prediction/worker.py
birdnet/acoustic_models/inference_pipeline/__init__.py
birdnet/acoustic_models/inference_pipeline/api.py
birdnet/acoustic_models/inference_pipeline/configs.py
birdnet/acoustic_models/inference_pipeline/encoding_strategy.py
birdnet/acoustic_models/inference_pipeline/logs.py
birdnet/acoustic_models/inference_pipeline/prediction_strategy.py
birdnet/acoustic_models/inference_pipeline/processes.py
birdnet/acoustic_models/inference_pipeline/resources.py
birdnet/acoustic_models/inference_pipeline/session.py
birdnet/acoustic_models/inference_pipeline/strategy.py
birdnet/acoustic_models/perch_v2/__init__.py
birdnet/acoustic_models/perch_v2/model.py
birdnet-0.2.11.dist-info/licenses/LICENSE.md
birdnet-0.2.11.dist-info/METADATA
birdnet-0.2.11.dist-info/WHEEL
birdnet-0.2.11.dist-info/entry_points.txt
birdnet-0.2.11.dist-info/top_level.txt
birdnet-0.2.11.dist-info/RECORD
