Metadata-Version: 2.4
Name: birdnet
Version: 0.2.11
Summary: A Python library for identifying bird species by their sounds.
Author: Stefan Taubert
Maintainer: Stefan Taubert
License: MIT
Project-URL: Homepage, https://github.com/birdnet-team/birdnet
Project-URL: Issues, https://github.com/birdnet-team/birdnet/issues
Project-URL: Repository, https://github.com/birdnet-team/birdnet.git
Project-URL: Changelog, https://github.com/birdnet-team/birdnet/blob/master/CHANGELOG.md
Keywords: birds,deep-learning,birdsong,acoustic-monitoring,bioacoustics
Classifier: Development Status :: 4 - Beta
Classifier: Operating System :: OS Independent
Classifier: Operating System :: MacOS
Classifier: Operating System :: POSIX
Classifier: Operating System :: POSIX :: BSD
Classifier: Operating System :: POSIX :: Linux
Classifier: Operating System :: Unix
Classifier: Operating System :: Microsoft :: Windows
Classifier: Programming Language :: Python
Classifier: Programming Language :: Python :: 3
Classifier: Programming Language :: Python :: 3.11
Classifier: Programming Language :: Python :: 3.12
Classifier: Programming Language :: Python :: 3.13
Classifier: License :: OSI Approved :: MIT License
Requires-Python: <3.14,>=3.11
License-File: LICENSE.md
Requires-Dist: soundfile>=0.11.0
Requires-Dist: scipy>=1.8.0
Requires-Dist: ordered-set>=4.1.0
Requires-Dist: tqdm>=4.64.0
Requires-Dist: numpy>=1.22.0
Requires-Dist: pandas>=1.4.0
Requires-Dist: psutil>=5.9.0
Requires-Dist: pyarrow>=7.0.0
Requires-Dist: kagglehub>=0.3.13
Requires-Dist: tensorflow>=2.8.0; sys_platform != "darwin" or platform_machine != "x86_64"
Requires-Dist: tensorflow<2.17,>=2.8.0; sys_platform == "darwin" and platform_machine == "x86_64"
Requires-Dist: ai-edge-litert>=2.0.2; python_version < "3.13" and sys_platform == "linux"
Provides-Extra: and-cuda
Requires-Dist: tensorflow[and-cuda]>=2.8.0; extra == "and-cuda"
Provides-Extra: repro
Requires-Dist: soundfile==0.12.1; extra == "repro"
Requires-Dist: scipy==1.16.3; extra == "repro"
Requires-Dist: ordered-set==4.1.0; extra == "repro"
Requires-Dist: tqdm==4.67.1; extra == "repro"
Requires-Dist: numpy==2.1.0; extra == "repro"
Requires-Dist: pandas==2.3.3; extra == "repro"
Requires-Dist: psutil==7.1.3; extra == "repro"
Requires-Dist: pyarrow==22.0.0; extra == "repro"
Requires-Dist: kagglehub==0.3.13; extra == "repro"
Requires-Dist: tensorflow==2.20.0; (sys_platform == "linux" or (sys_platform == "darwin" and platform_machine == "arm64") or (sys_platform == "windows" and platform_machine == "amd64")) and extra == "repro"
Requires-Dist: ai-edge-litert==2.0.3; (python_version < "3.13" and sys_platform == "linux") and extra == "repro"
Requires-Dist: absl-py==2.3.1; extra == "repro"
Requires-Dist: astunparse==1.6.3; extra == "repro"
Requires-Dist: backports.strenum==1.2.8; extra == "repro"
Requires-Dist: certifi==2025.11.12; extra == "repro"
Requires-Dist: cffi==2.0.0; extra == "repro"
Requires-Dist: charset-normalizer==3.4.4; extra == "repro"
Requires-Dist: flatbuffers==25.9.23; extra == "repro"
Requires-Dist: gast==0.6.0; extra == "repro"
Requires-Dist: google-pasta==0.2.0; extra == "repro"
Requires-Dist: grpcio==1.76.0; extra == "repro"
Requires-Dist: h5py==3.15.1; extra == "repro"
Requires-Dist: idna==3.11; extra == "repro"
Requires-Dist: keras==3.12.0; extra == "repro"
Requires-Dist: libclang==18.1.1; extra == "repro"
Requires-Dist: Markdown==3.10; extra == "repro"
Requires-Dist: markdown-it-py==4.0.0; extra == "repro"
Requires-Dist: MarkupSafe==3.0.3; extra == "repro"
Requires-Dist: mdurl==0.1.2; extra == "repro"
Requires-Dist: ml_dtypes==0.5.4; extra == "repro"
Requires-Dist: namex==0.1.0; extra == "repro"
Requires-Dist: opt_einsum==3.4.0; extra == "repro"
Requires-Dist: optree==0.18.0; extra == "repro"
Requires-Dist: packaging==25.0; extra == "repro"
Requires-Dist: pillow==12.0.0; extra == "repro"
Requires-Dist: protobuf==6.33.1; extra == "repro"
Requires-Dist: pycparser==2.23; extra == "repro"
Requires-Dist: Pygments==2.19.2; extra == "repro"
Requires-Dist: python-dateutil==2.9.0.post0; extra == "repro"
Requires-Dist: pytz==2025.2; extra == "repro"
Requires-Dist: pyyaml==6.0.3; extra == "repro"
Requires-Dist: requests==2.32.5; extra == "repro"
Requires-Dist: rich==14.2.0; extra == "repro"
Requires-Dist: setuptools==80.9.0; extra == "repro"
Requires-Dist: six==1.17.0; extra == "repro"
Requires-Dist: tensorboard==2.20.0; extra == "repro"
Requires-Dist: tensorboard-data-server==0.7.2; extra == "repro"
Requires-Dist: termcolor==3.2.0; extra == "repro"
Requires-Dist: typing_extensions==4.15.0; extra == "repro"
Requires-Dist: tzdata==2025.2; extra == "repro"
Requires-Dist: urllib3==2.5.0; extra == "repro"
Requires-Dist: Werkzeug==3.1.3; extra == "repro"
Requires-Dist: wheel==0.45.1; extra == "repro"
Requires-Dist: wrapt==2.0.1; extra == "repro"
Provides-Extra: tests
Requires-Dist: uv>=0.9.7; extra == "tests"
Requires-Dist: pytest>=8.4.2; extra == "tests"
Requires-Dist: pytest-cov>=7.0.0; extra == "tests"
Requires-Dist: pytest-xdist>=3.8.0; extra == "tests"
Requires-Dist: pytest-timeout>=2.4.0; extra == "tests"
Requires-Dist: mypy>=1.18.2; extra == "tests"
Requires-Dist: ruff>=0.14.4; extra == "tests"
Provides-Extra: dev
Requires-Dist: jupyter; extra == "dev"
Requires-Dist: uv; extra == "dev"
Requires-Dist: ruff; extra == "dev"
Requires-Dist: mypy; extra == "dev"
Requires-Dist: rope; extra == "dev"
Requires-Dist: build; extra == "dev"
Requires-Dist: twine; extra == "dev"
Requires-Dist: scipy-stubs; extra == "dev"
Requires-Dist: tuna; extra == "dev"
Requires-Dist: pyarrow-stubs; extra == "dev"
Requires-Dist: types-tqdm; extra == "dev"
Requires-Dist: types-requests; extra == "dev"
Requires-Dist: pandas-stubs; extra == "dev"
Requires-Dist: types-tensorflow; extra == "dev"
Dynamic: license-file
